ember_inspect-0.1.0.dist-info/METADATA
ember_inspect-0.1.0.dist-info/WHEEL
ember_inspect-0.1.0.dist-info/entry_points.txt
ember_inspect/.gitignore
ember_inspect/__init__.py
ember_inspect/controller.py
ember_inspect/eval.py
ember_inspect/model_api.py
ember_inspect/provider.py
ember_inspect-0.1.0.dist-info/RECORD
