Metadata-Version: 2.1
Name: ember-inspect
Version: 0.1.0
Summary: Use Goodfire Ember API with UK-AISI Inspect AI
Author-Email: Daniel Tan <dtch1997@users.noreply.github.com>
License: MIT
Requires-Python: >=3.10
Requires-Dist: goodfire>=0.3.4
Requires-Dist: openai>=1.59.6
Requires-Dist: inspect-ai>=0.3.57
Provides-Extra: examples
Requires-Dist: ipykernel>=6.29.5; extra == "examples"
Requires-Dist: python-dotenv>=1.0.1; extra == "examples"
Provides-Extra: dev
Requires-Dist: pytest>=8.3.4; extra == "dev"
